crossbarhttp/__init__.py
crossbarhttp/compat.py
crossbarhttp/crossbarhttp.py
crossbarhttp3-1.1.dist-info/DESCRIPTION.rst
crossbarhttp3-1.1.dist-info/METADATA
crossbarhttp3-1.1.dist-info/RECORD
crossbarhttp3-1.1.dist-info/WHEEL
crossbarhttp3-1.1.dist-info/metadata.json
crossbarhttp3-1.1.dist-info/top_level.txt
